muxi_llm/.version
muxi_llm/__init__.py
muxi_llm/audio.py
muxi_llm/chat_completion.py
muxi_llm/client.py
muxi_llm/completion.py
muxi_llm/config.py
muxi_llm/embedding.py
muxi_llm/errors.py
muxi_llm/files.py
muxi_llm/image.py
muxi_llm/models.py
muxi_llm/speech.py
muxi_llm/validators.py
muxi_llm/providers/__init__.py
muxi_llm/providers/base.py
muxi_llm/providers/fallback.py
muxi_llm/providers/openai.py
muxi_llm/types/__init__.py
muxi_llm/types/common.py
muxi_llm/utils/__init__.py
muxi_llm/utils/fallback.py
muxi_llm/utils/retry.py
muxi_llm/utils/streaming.py
muxi_llm/utils/token_counter.py
muxi_llm-0.1.2.dist-info/licenses/LICENSE
muxi_llm-0.1.2.dist-info/METADATA
muxi_llm-0.1.2.dist-info/WHEEL
muxi_llm-0.1.2.dist-info/top_level.txt
muxi_llm-0.1.2.dist-info/RECORD
