Metadata-Version: 2.4
Name: muxi-llm
Version: 0.1.2
Summary: A unified interface for interacting with large language models from various providers - a complete drop-in replacement for OpenAI's client
Home-page: https://github.com/muxi-ai/llm
Author: Ran Aroussi
Author-email: Ran Aroussi <ran@aroussi.com>
License: Apache-2.0
Project-URL: Homepage, https://github.com/muxijs/muxi
Project-URL: Documentation, https://docs.muxi.io
Project-URL: Issues, https://github.com/muxijs/muxi/issues
Classifier: Development Status :: 3 - Alpha
Classifier: Intended Audience :: Developers
Classifier: License :: OSI Approved :: GNU Affero General Public License v3
Classifier: Programming Language :: Python :: 3
Classifier: Programming Language :: Python :: 3.10
Classifier: Programming Language :: Python :: 3.11
Classifier: Topic :: Software Development :: Libraries :: Python Modules
Requires-Python: >=3.10
License-File: LICENSE
Dynamic: author
Dynamic: home-page
Dynamic: license-file
Dynamic: requires-python
